pykidgui/__init__.py
pykidgui/pykidgui.py
pykidgui/test.py
pykidgui-2.1.5.dist-info/METADATA
pykidgui-2.1.5.dist-info/WHEEL
pykidgui-2.1.5.dist-info/top_level.txt
pykidgui-2.1.5.dist-info/RECORD
