Metadata-Version: 2.1
Name: pykidgui
Version: 2.1.5
Summary: Simple gui de python para uso rapido e pratico / Simple python gui for quick and practical use
Home-page: https://github.com/ronanbastos/pykidgui
Author: Ronan Bastos
Author-email: Ronanbastos@hotmail.com
Classifier: Programming Language :: Python :: 3
Classifier: License :: OSI Approved :: MIT License
Classifier: Operating System :: OS Independent
Requires-Python: >=3.6
